caneth/__init__.py
caneth/cli.py
caneth/client.py
caneth/py.typed
caneth/utils.py
caneth-0.3.2.dist-info/licenses/LICENSE
caneth-0.3.2.dist-info/METADATA
caneth-0.3.2.dist-info/WHEEL
caneth-0.3.2.dist-info/entry_points.txt
caneth-0.3.2.dist-info/top_level.txt
caneth-0.3.2.dist-info/RECORD
