Metadata-Version: 2.4
Name: caneth
Version: 0.3.2
Summary: Asyncio CAN client for Waveshare 2-CH-CAN-TO-ETH with auto-reconnect and CLI
Author: Klaudiusz Staniek
License-Expression: MIT
Project-URL: Homepage, https://github.com/kstaniek/caneth
Project-URL: Documentation, https://kstaniek.github.io/caneth/
Project-URL: Source, https://github.com/kstaniek/caneth
Project-URL: Issues, https://github.com/kstaniek/caneth/issues
Project-URL: Changelog, https://github.com/kstaniek/caneth/releases
Classifier: Programming Language :: Python :: 3
Classifier: Programming Language :: Python :: 3 :: Only
Classifier: Framework :: AsyncIO
Classifier: Topic :: System :: Networking
Classifier: Typing :: Typed
Classifier: Operating System :: OS Independent
Requires-Python: >=3.10
License-File: LICENSE
Dynamic: license-file
